Workbook

Sheet 使い方
A1: ■ このファイルの使い方
A2: 1. 『アタックリスト』の黄色の列（担当者〜メモ）が入力欄です。ステータスはプルダウンから選んでください。
A3: 2. 優先度：A＝規格商品がなく中規模で集客課題が見える／B＝適合度が中くらい／C＝情報不足、または他FC加盟済み
A4: 3. 次回アクション日が今日以前で、まだ完了していない行は赤く表示されます。
A5: 4. 見送り・対象外にした行はグレー表示になります。
A6: 5. 『サマリー』は県別・ステータス別の件数を自動で集計します（リスト下に追記した行も、200行先まで集計されます）。
A8: ■ データについての注意
A9: ・会社情報は2026年10月時点のWeb検索結果をもとにしています。社名・規模・FC加盟状況は、アプローチ前に公式サイトで確認してください。
A10: ・確認できなかった項目は空欄のままにしています（推測では埋めていません）。
A11: ・LIFE X既存加盟店は除外済みです（『除外_既存加盟店』シート）。

Sheet アタックリスト
A1: No | B1: 優先度 | C1: 都道府県 | D1: 市区町村 | E1: 会社名 | F1: 公式サイト | G1: 主力事業・商品 | H1: 規模（確認できた範囲） | I1: 競合FC加盟状況 | J1: LIFE Xが刺さる理由 | K1: 根拠URL | L1: 担当者 | M1: ステータス | N1: 初回接触日 | O1: 次回アクション日 | P1: 次回アクション内容 | Q1: 先方キーマン | R1: メモ
A2: 1 | B2: A | C2: 神奈川県 | D2: 厚木市 | E2: 株式会社厚木地所 | G2: 県央エリアの不動産売買・仲介・自社分譲。減震パッキン工法の「エコファミリー」住宅を建築 | H2: 住宅建設31期で累計526棟（年平均約17棟と算出） | J2: 「良質な住宅を低価格で」を掲げ不動産集客の導線を持つ一方、高性能な規格商品は見当たらず、LIFE Xで商品力を補える | K2: https://tsukulink.net/kanagawa/city_142123/764560 | M2: 未着手
A3: 2 | B3: A | C3: 神奈川県 | D3: 相模原市 | E3: 相陽建設株式会社 | G3: 1970年創業の総合建設。注文住宅中心で主力は外断熱・二重通気の「ソーラーサーキットの家」、自然素材リフォームも | H3: 正社員規模推定33名（SalesNow） | I3: ソーラーサーキット工法採用（工法ネットワーク。住宅FCかは未確認） | J3: 高性能注文住宅が主体で、低価格帯の規格商品を持っている様子がなく、LIFE Xの1,890万円〜規格住宅で一次取得層を取り込める | K3: https://salesnow.jp/db/companies/jcbpca0vj3wg63wd ; https://crexgroup.com/ja/home-building/region/sagamihara-construction-company-list/ | M3: 未着手
A4: 3 | B4: A | C4: 神奈川県 | D4: 茅ヶ崎市 | E4: 大勝建設株式会社 | F4: https://www.daikatsu.plus/ | G4: 創業110年超の建設・住宅・不動産会社。自由設計・全棟長期優良住宅・耐震等級3の注文住宅（＋DAIKATSU） | H4: 資本金2,500万円、創業114年（Yahoo不動産・会社情報） | J4: 自由設計の注文が主体で規格商品が見えず、耐震等級3の土台がある分、断熱等級6・太陽光標準の規格商品を足しやすい | K4: https://realestate.yahoo.co.jp/company/used/bc00023294/ ; https://www.daikatsu.plus/ | M4: 未着手
A5: 4 | B5: B | C5: 神奈川県 | D5: 平塚市 | E5: 株式会社阿部建業 | G5: 創業55年超、湘南西部（平塚・茅ヶ崎・伊勢原・秦野等）の注文住宅・リフォーム・不動産。「コミコミ注文住宅」「平屋の家ふらっと君16」 | J5: パッケージ商品はあるが断熱等級4が標準のため、等級6・太陽光標準の規格住宅に上位互換として置き換える提案ができる | K5: https://compalyze.co.jp/company/6021001036109 ; https://www.e-mansion.co.jp/bbs/thread/11219/ | M5: 未着手
A6: 5 | B6: B | C6: 神奈川県 | D6: 横浜市金沢区 | E6: 大栄建設株式会社 | G6: 金沢区で地域密着35年。土地探し・資金計画から注文住宅、リフォーム、耐震補強まで | J6: リフォーム寄りの小規模工務店のようで、新築集客の目玉になる規格商品が無い | K6: https://www.biz.ne.jp/company/daiei1101/ | M6: 未着手
A7: 6 | B7: B | C7: 神奈川県 | D7: 茅ヶ崎市 | E7: 株式会社加賀妻工務店 | F7: http://www.kagatuma.co.jp/ | G7: 約50年の地域工務店。国産材・自然素材の木造住宅、大型リノベーション、耐震工事、不動産 | H7: 正社員規模推定18名（SalesNow） | J7: 高価格帯の自然素材注文住宅やリノベーションが主体で、若年層向けの規格商品が無い | K7: https://www.biz.ne.jp/corporation/26676/ ; https://salesnow.jp/db/companies/jcbpyxufanr08sdk | M7: 未着手
A8: 7 | B8: B | C8: 神奈川県 | D8: 藤沢市 | E8: サンキホーム株式会社 | F8: https://www.sankihome.co.jp/ | G8: 藤沢・茅ヶ崎・鎌倉・逗子の湘南エリアで天然素材の健康住宅（「緑の柱」採用）を手がける | J8: 天然素材の注文住宅が主体で、ローコスト・規格の品ぞろえが確認できない | K8: https://www.city.fujisawa.kanagawa.jp/documents/33414/r5jisseki_sankihome.pdf ; https://www.sankihome.co.jp/ | M8: 未着手
A9: 8 | B9: C | C9: 神奈川県 | E9: 神奈川エコハウス株式会社 | G9: 1972年設立。「健康と住環境」を重視した注文住宅。神奈川県産桧、基礎断熱、エアサイクル工法。港北の無添加住宅モデルハウス | I9: 無添加住宅のモデルハウスを運営との情報あり（無添加住宅ネットワークへの加盟を要確認） | J9: 健康住宅の高単価注文が軸で、性能を前に出した低価格規格帯が無い | K9: https://www.e-mansion.co.jp/bbs/thread/11729/ ; https://compalyze.co.jp/company/8021002003659 | M9: 未着手
A10: 9 | B10: C | C10: 神奈川県 | E10: 石原工務店 | F10: https://www.ishihara396.com/ | G10: 湘南エリア中心にシンプルで高性能な家づくり | J10: シンプル・高性能という方向性がLIFE Xと近く、商品化を後押しできる余地がある | K10: https://www.ishihara396.com/useful/3253/ | M10: 未着手
A11: 10 | B11: C | C11: 神奈川県 | E11: かつ七興産 | G11: 湘南の高性能注文住宅。HEAT20 G2標準、G3対応 | H11: 年間100棟以上（比較サイト記載） | J11: 棟数が対象の上限を超えるうえ性能も既に高く、適合度は低い | K11: https://local-time.jp/shonan-komuten/ | M11: 未着手
A12: 11 | B12: C | C12: 神奈川県 | D12: 厚木市 | E12: 民家工房常栄 | G12: 国産材・地元神奈川の木を使った自然派住宅 | J12: 自然派の注文住宅に特化しており、価格帯を広げる規格商品が無いとみられる | K12: https://www.e-mansion.co.jp/bbs/thread/10070/ | M12: 未着手
A13: 12 | B13: C | C13: 神奈川県 | D13: 小田原市 | E13: 株式会社江原工務店 | G13: 小田原拠点の木造注文住宅の販売・設計・施工、リフォーム・増改築 | J13: 県西部の木造注文工務店で、規格・高性能を売りにした商品が確認できない | K13: https://compalyze.co.jp/company/4021001034816 | M13: 未着手
A14: 13 | B14: C | C14: 神奈川県 | D14: 小田原市 | E14: 有限会社片山工務店 | G14: 昭和55年創業。小田原市内を中心に木造注文住宅 | J14: 小規模の木造注文工務店で、新規集客用の商品を持っていない | K14: https://www.seikatsu-guide.com/info/14/14206/7/ | M14: 未着手
A15: 14 | B15: C | C15: 神奈川県 | D15: 川崎市 | E15: 有限会社太洋建設 | G15: 昭和33年に田中工務店として開業。地域密着の在来木造住宅 | J15: 在来木造の老舗で、規格・高性能の商品が無いとみられる | K15: https://crexgroup.com/ja/home-building/region/kawasaki-city-construction-company-ranking-selection/ | M15: 未着手
A16: 15 | B16: C | C16: 神奈川県 | D16: 横浜市旭区 | E16: 有限会社大内工務店 | G16: 55年以上の地域工務店。自社大工による在来木造住宅、共同住宅、店舗、リフォーム | J16: 自社大工の施工力はあるが、商品・集客の仕組みが見えない | K16: https://itp.ne.jp/zenkoku/kanagawa/yokohamashi-kanagawaku/sammaichiyo/146465800200000899 | M16: 未着手
A17: 16 | B17: C | C17: 神奈川県 | D17: 相模原市 | E17: ギミックデザイン | G17: 「デザイン×性能×コスト」を掲げる設計事務所兼工務店。建築家が設計から現場まで一貫して担当 | J17: デザインとコストを重視する方針が、LIFE Xのデザイン規格住宅と重なる | K17: https://crexgroup.com/ja/home-building/region/sagamihara-construction-company-list/ | M17: 未着手
A18: 17 | B18: C | C18: 神奈川県 | D18: 茅ヶ崎市 | E18: 株式会社湘南渡辺 | G18: 1949年創業の一級建築士事務所。設計・新築・リフォーム・不動産 | J18: 設計と不動産の両方を持っており、規格住宅を加えれば土地とセットで売る導線が作れる | K18: https://www.e-mansion.co.jp/bbs/thread/673787/ | M18: 未着手
A19: 18 | B19: A | C19: 千葉県 | D19: 八街市 | E19: 株式会社工藤工務店 | G19: 1981年創業。FPウレタン断熱パネルの「FPの家」（UA値0.46以下・C値0.5以下）、自社大工施工 | H19: 累計700棟以上 | I19: FPの家（FPグループ工法ネットワーク）採用 | J19: 自社大工の中規模工務店でFPの高単価注文が主体のため、低価格の規格ラインを追加できる | K19: https://compalyze.co.jp/company/7011501006180 ; https://news.mynavi.jp/real-estate-assessment/73482 | M19: 未着手
A20: 19 | B20: A | C20: 千葉県 | D20: 市川市 | E20: 株式会社ダイシュウ | F20: https://www.daishu.co.jp/ | G20: 創業37年の工務店・一級建築士事務所。無垢材・漆喰で高耐震・高断熱の注文住宅（市川・松戸・船橋） | H20: 累計建築実績3,011棟（自社表記） | J20: 自然素材の高単価注文が主体で、1,000万円台の規格住宅を加えれば一次取得層の取りこぼしを拾える | K20: https://www.daishu.co.jp/workarea/%E8%88%B9%E6%A9%8B%E5%B8%82/ | M20: 未着手
A21: 20 | B21: B | C21: 千葉県 | E21: ウェルカムホーム | F21: https://www.welcome-home.jp/ | G21: 創業30年。デザイン注文住宅・高性能住宅。船橋・習志野・市川の一部・八千代が対応エリア | J21: デザインと高性能を打ち出す方向性がLIFE Xと合い、規格版を追加する余地がある | K21: https://www.welcome-home.jp/funabasi/ | M21: 未着手
A22: 21 | B22: B | C22: 千葉県 | D22: 八千代市 | E22: 木のすまい工房 | G22: 2010年創業の木の注文住宅 | H22: 2022年施工実績40棟 | J22: 年40棟の中規模で伸びている会社であり、規格商品を加えればさらに伸ばせる | K22: https://akitekt.net/koumutenmatome-1-27/ | M22: 未着手
A23: 22 | B23: B | C23: 千葉県 | D23: 千葉市 | E23: 創建住販 | G23: 平成元年に千葉市で開業した注文住宅会社。千葉市・市原市・四街道市が対応エリア | H23: 累計引き渡し2,000棟以上、年間約80棟以上 | J23: 棟数規模が対象帯の上位にあり、高性能な規格商品を加えれば商品の幅を広げられる | K23: https://news.mynavi.jp/real-estate-assessment/73482 | M23: 未着手
A24: 23 | B24: B | C24: 千葉県 | D24: 千葉市 | E24: 秋葉工務店 | G24: エアコン1台で快適な高断熱住宅 | H24: 創業20年で施工実績200棟超（年平均約10棟と算出） | J24: 小〜中規模の高断熱工務店で、規格商品を加えれば棟数を伸ばせる | K24: https://news.mynavi.jp/real-estate-assessment/73482 | M24: 未着手
A25: 24 | B25: B | C25: 千葉県 | D25: 千葉市稲毛区 | E25: 秋田建設工業株式会社 | G25: 1970年設立。木造2×4住宅が主力、自社設計・自社施工。大規模木造ホテル・店舗なども | H25: 従業員25名、資本金1億円、最近の年間完成棟数100棟超（求人情報） | J25: 2×4の自社施工体制が整っているので、規格住宅を加えれば受注効率を上げられる | K25: https://en-ambi.com/job/j-5351318/ | M25: 未着手
A26: 25 | B26: B | C26: 千葉県 | D26: 成田市 | E26: ヒラヤマホーム株式会社 | G26: 1901年木材業創業の老舗。注文住宅・リフォーム。コミコミ価格の「ファミールWX」プラン | J26: コミコミの規格的プランは既にあるため、性能（断熱等級6・太陽光標準）での差し替えを提案できる | K26: https://www.value-press.com/pressrelease/159201 ; https://www.biz.ne.jp/company/manahome/ | M26: 未着手
A27: 26 | B27: B | C27: 千葉県 | D27: 旭市 | E27: 有限会社丸富士工務店 | G27: 創業50年。営業専任を置かず専属担当が設計・施工監理・アフターまで担う自社責任施工 | J27: 営業担当がおらず集客力が弱いとみられ、FCの集客支援と規格商品が効く | K27: https://tsukulink.net/chiba/city_121011/254263 | M27: 未着手
A28: 27 | B28: B | C28: 千葉県 | D28: 船橋市 | E28: 株式会社本間工務店 | G28: ヒアリングから設計・施工までワンストップの注文住宅。高断熱・独自保証・設計力 | H28: 施工経験300棟以上 | J28: 設計力を売りにした注文住宅が中心で、規格商品の情報が無い | K28: https://funabashi.mypl.net/article/kurashi_funabashi/86372 ; https://honma-ltd.jp/media/chibakenn/ | M28: 未着手
A29: 28 | B29: B | C29: 千葉県 | D29: 茂原市 | E29: 協和ハウジング | F29: https://www.kyowa-housing.co.jp/ | G29: 1977年創業。茂原本社・東金支店の地域密着注文住宅 | J29: 外房エリアの地場ビルダーで、大手やローコスト系と競う中で高性能規格住宅が武器になる | K29: https://www.kyowa-housing.co.jp/ | M29: 未着手
A30: 29 | B30: C | C30: 千葉県 | D30: 佐倉市 | E30: さくら住建 | G30: 44年の歴史。「家族がずっとつながる家」を掲げる注文住宅 | J30: 地域密着の注文工務店で、商品ラインの拡充余地がある | K30: https://www.houzz.jp/professionals/general-contractor/%E4%BD%90%E5%80%89%E5%B8%82-04-jp-probr0-bo~t_16120~r_2111215 | M30: 未着手
A31: 30 | B31: C | C31: 千葉県 | D31: 八千代市 | E31: 木ここち家ラボ（オカムラホーム） | G31: 1995年創業の木の注文住宅 | J31: 地域の木造注文工務店で、規格・ローコスト帯の商品が確認できない | K31: https://akitekt.net/koumutenmatome-1-27/ | M31: 未着手
A32: 31 | B32: C | C32: 千葉県 | D32: 君津市 | E32: 株式会社君津住宅 | G32: 1990年設立。高品質・低価格の注文住宅。木更津・君津・茂原に展示場、完全反響型営業 | H32: 従業員250名（doda） | J32: 規模が対象帯を超え、低価格商品も既に持っているため適合度は低い | K32: https://doda.jp/DodaFront/View/CompanyJobs/j_id__10005586452/ | M32: 未着手
A33: 32 | B33: C | C33: 千葉県 | D33: 柏市 | E33: 株式会社グリーンホーム | G33: 建築・不動産の総合サービス。新築は完全自由設計 | J33: 完全自由設計が主体で、不動産の顧客向けに規格住宅を売る導線が作れる | K33: https://crexgroup.com/ja/home-building/region/kashiwa-city-builder-ranking/ | M33: 未着手
A34: 33 | B34: C | C34: 千葉県 | D34: 流山市 | E34: 有限会社綱木工業（ハウジングツナキ） | G34: 耐震補強・新築・リフォーム。流山・我孫子・松戸・柏が対応エリア | J34: 耐震・リフォーム中心で、新築の集客商品として規格住宅を導入する余地がある | K34: https://www.biz.ne.jp/corporation/29241/ | M34: 未着手
A35: 34 | B35: C | C35: 千葉県 | D35: 船橋市 | E35: 株式会社フジ設計企画 | G35: 1984年創業。地域密着の工務店でアフターフォローに注力 | J35: 地域密着の中小工務店で、商品力・集客を強化する余地がある | K35: https://funabashi.mypl.net/article/kurashi_funabashi/86372 | M35: 未着手
A36: 35 | B36: C | C36: 千葉県 | D36: 船橋市 | E36: 日動建設株式会社 | G36: 創業40年以上。大工施工の木造住宅にこだわる地元工務店 | J36: 職人型の木造工務店で規格商品が無く、集客商品が必要とみられる | K36: https://funabashi.mypl.net/article/kurashi_funabashi/86372 | M36: 未着手
A37: 36 | B37: A | C37: 静岡県 | D37: 掛川市 | E37: 有限会社大忠工務店 | G37: 1979年創業。掛川中心に西部・中遠で木造注文住宅、リフォーム、寺社建築。企画にない自由設計が強み | J37: 「企画にない自由設計」を掲げる小規模工務店で規格商品が無く、若年層向けの低価格高性能商品で受注層を広げられる。 | K37: https://compalyze.co.jp/company/4080402018059 | M37: 未着手
A38: 37 | B38: A | C38: 静岡県 | D38: 沼津市 | E38: 株式会社芹工務店 | G38: 沼津で30年以上の地域密着工務店。新築注文住宅＋リフォーム、地元材の富士ひのき使用・デザインと性能の両立 | J38: 注文住宅一本で規格・価格訴求商品が見当たらず、富士ひのきの性能訴求と組み合わせた入口商品として規格住宅を提案しやすい。 | K38: https://en-gage.net/serikosaiyo_saiyo/work_17700223/ | M38: 未着手
A39: 38 | B39: B | C39: 静岡県 | E39: 有限会社富士ホームズデザイン | G39: 一級建築士事務所兼工務店。自由設計注文住宅中心（平屋・二世帯・店舗併用）、耐震等級3・制震・長期優良・断熱等級5以上標準 | J39: 性能仕様が近いので、規格化された断熱等級6・太陽光標準の商品へ移りやすく、口コミ評価がまちまちなため集客面の支援も効きそう。 | K39: https://www.e-mansion.co.jp/bbs/thread/212986/ | M39: 未着手
A40: 39 | B40: B | C40: 静岡県 | E40: 株式会社アオイ建築 | G40: ブランド「Hands Works」。新築・リフォーム・不動産、店舗併用住宅・美容室も対応。富士宮・富士・裾野で施工 | J40: デザイン系の自由設計が中心で、価格帯の低い規格ラインを追加する余地がある。 | K40: https://compalyze.co.jp/company/2080101011812 | M40: 未着手
A41: 40 | B41: B | C41: 静岡県 | D41: 富士市 | E41: 株式会社アフターホーム | G41: 富士・富士宮・沼津で1995年設立。完全自由設計＋コミコミ価格、「家賃並みの支払いで高品質住宅を」 | J41: 価格訴求型の自由設計で、規格化すれば原価・工期を下げられ、高性能（等級3・断熱6・太陽光）の訴求も足せる。 | K41: https://compalyze.co.jp/company/9080102016036 | M41: 未着手
A42: 41 | B42: B | C42: 静岡県 | D42: 富士市 | E42: エコフィールド株式会社 | F42: https://ecofield.jp/ | G42: 富士の麓で「自然と繋がるここちいい暮らし」を追求する地域密着工務店（富士市中里） | J42: ナチュラル系の自由設計が中心で、価格を抑えたい層向けの規格商品が見当たらない。 | K42: https://www.city.fuji.shizuoka.jp/documents/4226/kentikuissiki_2.pdf | M42: 未着手
A43: 42 | B43: B | C43: 静岡県 | D43: 富士市 | E43: 富士木材株式会社 | G43: 1913年創業の製材業から梱包・物流・住宅事業へ展開。住宅ブランド「フジモクの家」 | J43: 住宅は多角化事業の1部門なので、規格商品パッケージで住宅部門の営業効率を上げる提案ができる。 | K43: https://www.city.fuji.shizuoka.jp/documents/16146/2-2_fujiokuzai.pdf | M43: 未着手
A44: 43 | B44: B | C44: 静岡県 | D44: 掛川市 | E44: 株式会社原田工務店 | F44: https://haradakomuten.com/index.html | G44: 「ビリーブの家」ブランドの自由設計注文住宅。耐震等級3・高気密高断熱標準、総額「お引渡し価格」提示 | H44: 創立20年以上 | I44: 「ビリーブの家」ブランドで展開（FC・ネットワークかは未確認） | J44: 総額提示で価格を訴求する自由設計なので、規格化で原価・工期をさらに下げられる。 | K44: https://www.e-mansion.co.jp/bbs/thread/77347/ | M44: 未着手
A45: 44 | B45: B | C45: 静岡県 | D45: 沼津市 | E45: 株式会社藤田工務店 | F45: https://zero-fujita.com/ | G45: 総合建築の設計施工・リフォーム・不動産。無垢材・漆喰の高気密高断熱健康住宅「0宣言の家」が主力 | I45: 「0宣言の家」（住宅ネットワーク商品）を主力に展開 | J45: 自然素材の高単価帯が主力のため、若年層向けの低価格帯規格商品を補完として追加できる余地がある。 | K45: https://compalyze.co.jp/company/7080101000141 | M45: 未着手
A46: 45 | B46: B | C46: 静岡県 | D46: 浜松市 | E46: 株式会社ぬくもり工房 | G46: 「住たくeco工房」運営。住宅・店舗建築、リフォーム、外構、施設運営（ぬくもりの森）。1998年設立 | H46: 資本金300万円 | J46: 集客力（イエタテ西部1位）はあるので、受注の価格帯を広げる規格商品として提案できる。 | K46: https://www.revic.co.jp/pdf/news/2018/180329newsrelease.pdf | M46: 未着手
A47: 46 | B47: B | C47: 静岡県 | D47: 浜松市中央区 | E47: 株式会社木の香建築工房 | G47: 天然木・無垢材の木造軸組、長期優良住宅対応の注文住宅、土地探し・不動産 | H47: 従業員5名 | J47: 少人数で設計・営業の手が足りないとみられ、規格商品と本部の集客支援で受注を増やしやすい。 | K47: https://compalyze.co.jp/company/4080401013011 | M47: 未着手
A48: 47 | B48: B | C48: 静岡県 | D48: 浜松市浜名区 | E48: 都田建設株式会社 | G48: 1996年設立、木造注文住宅。デザイン性の高い商品スタイル（3スタイル）を展開 | H48: 社会保険被保険者44名／従業員65名（パート含む） | J48: 中規模で自由設計の注文住宅が主力のため、低価格帯の入口商品を追加できる余地がある（ブランド力は強い）。 | K48: https://compalyze.co.jp/company/2080401006396 | M48: 未着手
A49: 48 | B49: B | C49: 静岡県 | D49: 湖西市 | E49: 株式会社CRAFT | G49: 西部で20年以上の地域密着。CRAFT SELECTの「Arie」（長期優良）・「HUCK」（自然素材）・「HIRAYA」（平屋） | J49: 自社商品はあるものの低価格帯の高性能規格は見当たらず、ラインアップを補う提案ができる。 | K49: https://compalyze.co.jp/company/4080401011056 | M49: 未着手
A50: 49 | B50: B | C50: 静岡県 | D50: 藤枝市 | E50: 有限会社仲田工務店 | G50: 地域密着の一級建築士事務所。自然素材を多用した高性能注文住宅、リフォーム、構造調査 | J50: 小規模な自由設計の工務店で、商品化・集客の仕組みを外から取り入れる効果が大きい。 | K50: https://compalyze.co.jp/company/3080401003509 | M50: 未着手
A51: 50 | B51: C | C51: 静岡県 | D51: 三島市 | E51: 株式会社鈴木工務店 | G51: 1958年創業。伊豆箱根の旅館・ホテル建築で培った技術。住宅・集合住宅・商業施設まで総合建築 | H51: 従業員11-100名（求人情報） | I51: 競合FC加盟（R+house三島） | J51: R+houseで高価格帯デザイン住宅を扱っているため、ロイヤリティ無料の低価格帯規格で下の価格帯を補う提案になる。 | K51: https://mynavi-agent.jp/corpdetail/30451/ | M51: 未着手
A52: 51 | B52: C | C52: 静岡県 | D52: 浜松市 | E52: 株式会社寿建設 | G52: 注文住宅・店舗建設・リフォーム・不動産を総合的に手掛ける | J52: 住宅以外の事業も抱えており、注文住宅部門を規格化して効率を上げる余地がある（情報不足）。 | K52: https://compalyze.co.jp/company/4080401013011 | M52: 未着手
A53: 52 | B53: C | C53: 静岡県 | D53: 焼津市 | E53: 株式会社山田工務店 | G53: 新築HAPPY HOUSE、企画型注文住宅JUST LUCKY HOUSE（2019年〜）、リフォーム、建売の4事業 | H53: 従業員124人、資本金10百万円、1976年設立 | I53: 自社の企画型ブランドあり（JUST LUCKY HOUSE） | J53: 自社で規格商品を持つので適合度は低く、高性能仕様の別ブランドとしてなら検討余地がある程度。 | K53: https://www.r-agent.com/company/a9425/ | M53: 未着手
A54: 53 | B54: C | C54: 静岡県 | D54: 藤枝市 | E54: 西遠建設株式会社 | G54: 土木・河川改修を基盤とする建設会社。住宅はR+house藤枝として展開 | H54: 推定正社員約40名 | I54: 競合FC加盟（R+house藤枝） | J54: R+houseの高価格帯に加え、ロイヤリティ無料の規格住宅で下の価格帯を取り込める。 | K54: https://ouchi-keikaku.heteml.net/cyumonjyutaku-osusume-shizuoka/ | M54: 未着手
A55: 54 | B55: C | C55: 静岡県 | D55: 静岡市駿河区 | E55: 株式会社福工房 | F55: https://fukukobo-shizuoka.net/ | G55: 2025年に創業20年の住宅メーカー。静岡から愛知・神奈川・埼玉・千葉へ拡大中 | J55: 自社で広域展開する成長型のため、FC加盟の必要性は低いとみられる。 | K55: https://job.mynavi.jp/27/pc/search/corp201435/outline.html | M55: 未着手
A56: 55 | B56: A | C56: 愛知県 | D56: 一宮市 | E56: 河合工務店 | G56: 1970年創業。日本伝統の木造軸組工法にこだわった注文住宅 | J56: 老舗の在来工法による注文住宅一本で規格・ローコスト商品が見当たらず、若年層を取り込む規格商品として刺さりやすい。 | K56: https://life-designs.jp/webmagazine/housing-ichinomiya/ | M56: 未着手
A57: 56 | B57: A | C57: 愛知県 | D57: 春日井市 | E57: グリンホーム | G57: 1986年創業、春日井で完全自由設計住宅・分譲・リフォーム、多様な構造に対応 | J57: 30年以上の地場工務店で完全自由設計が中心、規格商品が見当たらない。 | K57: https://life-designs.jp/webmagazine/housing-kasugai/ | M57: 未着手
A58: 57 | B58: B | C58: 愛知県 | E58: スペースラボ | G58: 名古屋市〜尾張全域（本社から車1時間圏）、人生設計から考える家づくり | J58: 資金計画から提案するスタイルなので、価格が明快な規格商品と相性が良い。 | K58: https://news.mynavi.jp/real-estate-assessment/74057 | M58: 未着手
A59: 58 | B59: B | C59: 愛知県 | D59: 小牧市 | E59: 株式会社広和木材 | G59: 自社製材工場を持ち、無垢材をふんだんに使った住宅 | J59: 製材を自社で持つ強みがあり、規格住宅の構造材の供給と販売の両面で組みやすい。 | K59: https://base-on.com/media/aichi-komaki-city/ | M59: 未着手
A60: 59 | B60: B | C60: 愛知県 | D60: 岡崎市 | E60: セブンハウス | F60: https://sevenhouse.jp/ | G60: 岡崎中心に西三河（岡崎・豊田・安城など）で新築注文住宅・リフォーム・リノベ | J60: 西三河の地場工務店で、高性能規格の商品を追加できる余地がある。 | K60: https://sevenhouse.jp/ | M60: 未着手
A61: 60 | B61: B | C61: 愛知県 | D61: 春日井市 | E61: 三国住宅 | G61: 国産・自然素材の木の家、「安心・健康・自由」な家づくり | J61: 自然素材の自由設計が中心で、低価格帯の高性能規格商品で補完できる。 | K61: https://life-designs.jp/webmagazine/housing-kasugai/ | M61: 未着手
A62: 61 | B62: B | C62: 愛知県 | D62: 春日井市 | E62: 株式会社マスターズ | F62: https://www.likehome-masters.com/ | G62: 春日井・小牧・犬山・守山区・北名古屋で自由設計の家づくり | J62: 尾張北部の自由設計工務店で、規格商品により営業の生産性を上げられる。 | K62: https://life-designs.jp/webmagazine/housing-kasugai/ | M62: 未着手
A63: 62 | B63: B | C63: 愛知県 | D63: 江南市 | E63: 安井建設株式会社 | G63: ブランド「Home&nico」。耐震等級3・HEAT20 G2を標準 | J63: 性能仕様がLIFE Xと近く、規格の低価格ラインとして取り込みやすい。 | K63: https://realestate.news.mynavi.jp/housemaker-ranking/aichi-komuten-osusume | M63: 未着手
A64: 63 | B64: C | C64: 愛知県 | E64: 大原建設 | G64: 春日井・小牧中心に新築注文住宅・リフォーム・店舗設計 | J64: 注文住宅とリフォーム・店舗を兼業しており、新築の規格化で効率を上げられる（情報不足）。 | K64: https://life-designs.jp/webmagazine/housing-kasugai/ | M64: 未着手
A65: 64 | B65: C | C65: 愛知県 | E65: 株式会社善匠 | G65: フルオーダー住宅から規格住宅まで幅広い家づくり | I65: 自社の規格住宅あり | J65: 自社で規格住宅を持っており、適合度は低い。 | K65: https://news.mynavi.jp/real-estate-assessment/74057 | M65: 未着手
A66: 65 | B66: C | C66: 愛知県 | E66: 上村建設（ユースタイルハウス） | G66: ブランド「ユースタイルハウス」。くふうイエタテ2026上半期 愛知三河1位 | J66: 集客力は高いので、受注の価格帯を広げる規格商品として提案できる（詳細は要確認）。 | K66: https://www.sumailab.net/P23/A6/rankings/135/okazaki/ | M66: 未着手
A67: 66 | B67: C | C67: 愛知県 | E67: 吉川住建 | G67: 豊橋エリアで人気（イエタテ2025下半期 愛知三河1位） | J67: 東三河の有力工務店で、規格商品の有無を確認したうえで提案する（情報不足）。 | K67: https://www.sumailab.net/P23/A6/rankings/134/toyohashi/ | M67: 未着手
A68: 67 | B68: C | C68: 愛知県 | E68: 片桐建設 | G68: 豊橋エリアで人気（イエタテ2025下半期 愛知三河2位） | J68: 東三河の工務店で、規格商品の有無は要確認（情報不足）。 | K68: https://www.sumailab.net/P23/A6/rankings/134/toyohashi/ | M68: 未着手
A69: 68 | B69: C | C69: 愛知県 | E69: ユートピア建設 | G69: 豊橋エリアで人気（イエタテ2025下半期 愛知三河3位） | J69: 東三河の工務店で、規格商品の有無は要確認（情報不足）。 | K69: https://www.sumailab.net/P23/A6/rankings/134/toyohashi/ | M69: 未着手
A70: 69 | B70: C | C70: 愛知県 | E70: 小幡建設 | G70: 豊田エリアで人気（イエタテ2026上半期 愛知三河1位） | J70: 豊田エリアの工務店で、規格商品の有無は要確認（情報不足）。 | K70: https://www.sumailab.net/P23/A6/rankings/139/toyota/ | M70: 未着手
A71: 70 | B71: C | C71: 愛知県 | D71: 一宮市 | E71: 株式会社いわいハウジング | G71: 一宮市の工務店 | J71: 地場の工務店で、商品・集客の状況は追加確認が必要（情報不足）。 | K71: https://life-designs.jp/webmagazine/housing-ichinomiya/ | M71: 未着手
A72: 71 | B72: A | C72: 石川県 | D72: 七尾市 | E72: シティハウス産業株式会社 | F72: https://www.cityhouse.jp/ | G72: 七尾市・中能登町・志賀町・羽咋市の注文住宅。能登半島地震を受けて「命を守る家づくり」を打ち出す | H72: 1981年6月設立、正社員は推定7名、資本金1,000万円 | J72: 能登の小規模地場工務店で、復興の再建需要に向けて、耐震等級3で価格が明確な規格住宅を早く出せるLIFE Xが効く。 | K72: https://www.cityhouse.jp/ | M72: 未着手
A73: 72 | B73: A | C73: 石川県 | D73: 白山市 | E73: 西内工務店株式会社 | G73: 新築住宅・リフォーム・一般建築。独自の「WB HOUSE」（WB工法）を展開。一級建築士事務所 | H73: 創業以来1,000件超の設計施工実績（自社記載ベース） | I73: WB工法採用（工法ネットワーク。住宅FC加盟は未確認） | J73: 注文住宅中心で規格・ローコスト商品が見当たらず、金沢近郊の白山市で一次取得層向けの低価格高性能ラインを追加する余地がある。 | K73: https://itp.ne.jp/zenkoku/ishikawa/hakusanshi/narimachi/171304837300000899 | M73: 未着手
A74: 73 | B74: B | C74: 石川県 | D74: 小松市 | E74: 北出建築工房plus | F74: https://www.kitadekenchiku.jp/ | G74: 小松市・加賀市・能美市で耐震等級3・ZEHのデザイン住宅。建築士の代表が設計提案 | J74: 耐震3・ZEHの設計姿勢がLIFE Xの仕様と近く、設計者依存を減らす規格商品として提案しやすい。 | K74: https://www.kitadekenchiku.jp/ | M74: 未着手
A75: 74 | B75: B | C75: 石川県 | D75: 小松市 | E75: 大黒建設 | F75: https://daikokukensetsu.co.jp/ | G75: 1957年創業・3代続く小松の工務店。子育て・高齢者向けの注文住宅 | J75: 老舗の地場工務店で、若年の一次取得層に向けた明快な価格の規格住宅を補える。 | K75: https://daikokukensetsu.co.jp/ | M75: 未着手
A76: 75 | B76: B | C76: 石川県 | D76: 小松市 | E76: イング建築設計 | F76: https://ing-archi.com/ | G76: 自然素材を使った高性能・デザイン志向の注文住宅 | J76: デザインと性能を重視する設計系で、LIFE Xのデザイン規格住宅と方向性が合う。 | K76: https://ing-archi.com/ | M76: 未着手
A77: 76 | B77: B | C77: 石川県 | D77: 金沢市 | E77: 株式会社ひまわりほーむ | G77: 地域密着型ハウスメーカー。全棟長期優良住宅・全棟W断熱の高性能注文住宅。能登半島の復興支援も行う | H77: 1996年設立、資本金1億円、従業員65名（2025年5月現在）。拠点は石川・富山・東京 | J77: 高性能注文住宅が主力で、能登の復興需要や若年層に向けた価格訴求の規格ラインを補える。 | K77: https://www.bizreach.jp/job/view/3633864/ | M77: 未着手
A78: 77 | B78: B | C78: 石川県 | D78: 金沢市 | E78: 株式会社嶋源木建 | F78: https://www.uruoino-ie.jp/ | G78: 自然素材の注文住宅「うるおいの家」、新築・リフォーム（金沢市・白山市） | J78: 自然素材の注文住宅に特化しており、規格・ローコストの入口商品がない。 | K78: https://www.uruoino-ie.jp/ | M78: 未着手
A79: 78 | B79: B | C79: 石川県 | D79: 金沢市 | E79: たくみ工務店 | F79: https://takumi-build.co.jp/ | G79: 専属大工による注文住宅・新築戸建て | J79: 大工を抱える施工力型の工務店で、規格商品を加えれば集客と施工の稼働を平準化できる。 | K79: https://takumi-build.co.jp/ | M79: 未着手
A80: 79 | B80: B | C80: 石川県 | D80: 金沢市 | E80: 端工務店 | F80: https://hashi-koumuten.com/ | G80: 自然素材を使った高気密・高断熱の注文住宅（1981年創業） | J80: 高性能住宅のノウハウがあり、断熱等級6・太陽光標準のLIFE X仕様を受け入れやすい。 | K80: https://hashi-koumuten.com/ | M80: 未着手
A81: 80 | B81: C | C81: 石川県 | E81: 株式会社クロダハウス | G81: 北陸で建築一式・不動産・非住宅・注文住宅。スウェーデンハウスの販売施工、規格型セレクト住宅ainoe | I81: 競合FC加盟：R+house取扱。スウェーデンハウス販売施工、ainoe（規格型）取扱 | J81: 多ブランドを扱う会社で、ainoeと競合するため優先度は低い。 | K81: https://mynavi-agent.jp/corpdetail/30024/ | M81: 未着手
A82: 81 | B82: C | C82: 石川県 | E82: 石友ホーム（石友ホームグループ） | G82: 高気密・高断熱の自社開発工法による注文住宅 | H82: グループ従業員964名（2026年1月1日時点）、北陸エリア着工棟数17年連続No.1 | J82: 規模が過大で対象外に近く、競合把握のために記載。 | K82: https://hrmos.co/pages/ishitomo-recruit/jobs/2244697317863440384 | M82: 未着手
A83: 82 | B83: C | C83: 石川県 | D83: 白山市 | E83: 株式会社建築昌英 | G83: 木造注文住宅。年間施工棟数をあえて絞る方針 | J83: 少数精鋭型のため適合度は低めだが、規格ラインで受注の幅を広げる余地はある。 | K83: https://auka.jp/media/housemaker/housemaker-ishikawa/housemaker-isikawa-kanazawa | M83: 未着手
A84: 83 | B84: C | C84: 石川県 | D84: 金沢市 | E84: 株式会社國見工務店 | F84: https://www.kunimikoumuten.com/ | G84: 無垢材・自然素材の注文住宅、リノベーション | J84: 自然素材の注文住宅特化型で、低価格帯の商品を補完できる可能性がある。 | K84: https://www.kunimikoumuten.com/ | M84: 未着手
A85: 84 | B85: C | C85: 石川県 | D85: 金沢市 | E85: ジョイント21 | G85: 金沢・小松に店舗。土地探しから家づくりまで一貫対応（宅建業 石川県知事(6)第3535号） | J85: 不動産と住宅を兼業しており、土地とセットで売る規格住宅として販売しやすい。 | K85: https://toushi.homes.co.jp/bukkeninform/4615965/ | M85: 未着手
A86: 85 | B86: C | C86: 石川県 | D86: 金沢市 | E86: ニューハウス工業株式会社 | G86: 1966年創業の北陸地場ビルダー | H86: 北陸で14,000棟以上の施工実績（紹介記事記載） | J86: 規模が大きく狙いの棟数帯を超えるとみられるため、参考として記載。 | K86: https://job.mynavi.jp/27/pc/search/corp98557/outline.html | M86: 未着手
A87: 86 | B87: C | C87: 石川県 | D87: 鹿島郡中能登町 | E87: 若狭建設株式会社 | G87: 能登地域の工務店（詳細未確認） | J87: 能登の地場工務店で、復興の再建需要の受け皿になりうるが情報が不足している。 | K87: https://www.houzz.jp/professionals/general-contractor/c/%E7%9F%B3%E5%B7%9D%E7%9C%8C-%E9%B9%BF%E5%B3%B6%E9%83%A1%E4%B8%AD%E8%83%BD%E7%99%BB%E7%94%BA | M87: 未着手
A88: 87 | B88: A | C88: 香川県 | D88: 三豊市 | E88: 株式会社大河内工務店 | G88: 香川県西部中心の木造注文住宅（和風・洋風）と商業建築。大工館・カフェ「木きん堂」を運営、2019年に高松店 | H88: 1953年創業・1996年法人化。手掛けた家は1,500棟以上（紹介記事）。トータルハウジング大賞受賞歴 | J88: 中規模の注文住宅中心で、高松進出で集客を強化している段階にあり、規格・ローコストの入口商品を足す余地が大きい。 | K88: https://www.value-press.com/s/pressrelease/130699 | M88: 未着手
A89: 88 | B89: A | C89: 香川県 | D89: 丸亀市 | E89: 株式会社香川建築 | F89: https://www.kagawakentiku.com/ | G89: 新築注文住宅、古民家（木造和風）、一般住宅・店舗リフォーム、不動産 | H89: 創業1988年（昭和63年） | J89: 注文住宅・古民家・リフォームの兼業型で規格商品がなく、丸亀エリアの若年層向けの新築入口商品として刺さる。 | K89: https://www.kagawakentiku.com/ | M89: 未着手
A90: 89 | B90: A | C90: 香川県 | D90: 坂出市 | E90: 大塚建設株式会社 | F90: https://www.otsuka-cc.jp/ | G90: 自由設計の高性能住宅を手の届く価格で提供（耐震等級3・HEAT20 G2） | H90: 正社員は推定7名 | J90: 小規模ながら耐震3・高断熱の施工力があり、LIFE X仕様をすぐ導入でき、ブランド力の補強で集客を伸ばせる。 | K90: https://www.otsuka-cc.jp/ | M90: 未着手
A91: 90 | B91: B | C91: 香川県 | E91: 株式会社菅組 | G91: 1909年創業の地域建設会社。公共・商業・医療福祉・社寺の建築と住宅・リフォーム。環境方針あり | H91: 社員大工約20名 | J91: 総合建設が主体で、住宅部門に規格商品を加えれば稼働を安定させやすい。 | K91: https://job.mynavi.jp/28/pc/search/corp99482/is.html | M91: 未着手
A92: 91 | B92: B | C92: 香川県 | D92: さぬき市 | E92: 大川建設株式会社 | G92: 注文住宅・リフォーム・非住宅。全棟で耐震等級3相当の構造計算、長期優良住宅が標準。ZEHビルダー | H92: 創業59年 | I92: パナソニック「テクノストラクチャー」施工認定店（工法ネットワーク）、LIXILリフォームネット登録店 | J92: 高性能志向の注文住宅会社で、LIFE Xを低価格帯の補完商品として組み込みやすい。 | K92: https://compalyze.co.jp/company/6470001011035 | M92: 未着手
A93: 92 | B93: B | C93: 香川県 | D93: 坂出市 | E93: 株式会社レオックス | F93: https://www.reox.jp/ | G93: テクノストラクチャーによる耐震等級3・ZEHの注文住宅（坂出中心） | I93: パナソニック「テクノストラクチャー」採用（工法ネットワーク） | J93: 耐震3を実現する体制が整っており、低価格の規格ラインを補完できる。 | K93: https://panasonic.co.jp/phs/pasd/pb-techno/pb_search/detail.php?area=chugoku_shikoku&pref=kagawa&pb=P0413 | M93: 未着手
A94: 93 | B94: B | C94: 香川県 | D94: 坂出市 | E94: 株式会社ツヤマ | F94: http://www.tsuyama-h.jp/ | G94: 坂出市・宇多津町・丸亀市の注文住宅・新築戸建て | J94: 中讃エリアの注文住宅工務店で、規格商品の追加余地がある。 | K94: http://www.tsuyama-h.jp/ | M94: 未着手
A95: 94 | B95: B | C95: 香川県 | D95: 観音寺市 | E95: ハウスデザイン三協（三協ハウジング） | F95: https://www.k3kyo.co.jp/ | G95: 新築注文住宅 | J95: 県西部（観音寺）の注文住宅会社で、ローコスト帯の受け皿となる商品を補える。 | K95: https://www.k3kyo.co.jp/ | M95: 未着手
A96: 95 | B96: B | C96: 香川県 | D96: 高松市 | E96: 株式会社ロータリーハウス | G96: 長期優良住宅・自由設計の注文住宅、平屋に強い（2022年度の施主の約半数が平屋）。グループで不動産も | H96: ロータリーハウス・ホールディングスが2021年度に香川県・高松市商圏の注文住宅着工棟数総合No.1 | J96: 地場上位で規模は大きめだが、低価格の規格ラインを別ブランドとして持たせる提案ならありうる。 | K96: https://resemom.jp/release/prtimes/20230913/104104.html | M96: 未着手
A97: 96 | B97: B | C97: 香川県 | D97: 高松市 | E97: 高陽建設株式会社 | G97: 企画・製材・施工・アフターまで一貫の木造住宅。注文住宅・リノベ・規格住宅 | H97: 1960年設立、社会保険被保険者数9名 | I97: 自社の規格住宅あり | J97: 製材から一貫で手がける木造の会社。規格住宅はすでにあるが、高性能デザイン規格としての上位互換を提案できる。 | K97: https://compalyze.co.jp/company/4470001001467 | M97: 未着手
A98: 97 | B98: B | C98: 香川県 | D98: 高松市 | E98: エヌケー建設株式会社 | G98: 鉄骨住宅メーカーとして創業し、RC造・木造住宅・公共工事（学校・消防署等）を手がける総合建設 | H98: 従業員約32名、年商約15億円、1970年設立 | J98: 公共工事との兼業で、住宅は規格商品で効率よく受注を伸ばせる。 | K98: https://news.ksb.co.jp/article/15416864 | M98: 未着手
A99: 98 | B99: B | C99: 香川県 | D99: 高松市 | E99: アイラックホーム株式会社 | G99: 自然素材の注文住宅、不動産売買・宅地開発（1978年設立） | H99: 資本金300万円 | J99: 不動産と宅地開発を兼業しており、土地とセットで売る規格住宅として販売しやすい。 | K99: https://mynavi-agent.jp/corpdetail/29948/ | M99: 未着手
A100: 99 | B100: C | C100: 香川県 | E100: 株式会社日進堂 | G100: 香川の地元ビルダー（住宅・不動産）。ハウスドゥ高松中央店も運営 | H100: 香川県の戸建着工棟数で2010〜2024年度15年連続No.1（住宅産業研究所調べのランキング） | I100: ハウスドゥ（不動産FC）加盟店を運営 | J100: 県内最大手で対象規模を超えるため、競合把握として記載。 | K100: https://job.mynavi.jp/27/pc/search/corp89971/outline.html | M100: 未着手
...

Sheet サマリー
A1: LIFE X 加盟店開拓 アタックリスト サマリー
A2: 数値はすべて『アタックリスト』シートから数式で自動集計されます。
A4: 都道府県 | B4: A | C4: B | D4: C | E4: 合計 | F4: 接触済 | G4: 商談中以上 | H4: 加盟決定
A5: 神奈川県 | B5: =COUNTIFS(アタックリスト!$C$2:$C$305,$A5,アタックリスト!$B$2:$B$305,"A") -> 3 | C5: =COUNTIFS(アタックリスト!$C$2:$C$305,$A5,アタックリスト!$B$2:$B$305,"B") -> 4 | D5: =COUNTIFS(アタックリスト!$C$2:$C$305,$A5,アタックリスト!$B$2:$B$305,"C") -> 10 | E5: =SUM(B5:D5) -> 17 | F5: =COUNTIFS(アタックリスト!$C$2:$C$305,$A5,アタックリスト!$M$2:$M$305,"<>未着手",アタックリスト!$M$2:$M$305,"<>") -> 0 | G5: =COUNTIFS(アタックリスト!$C$2:$C$305,$A5,アタックリスト!$M$2:$M$305,"商談中")+COUNTIFS(アタックリスト!$C$2:$C$305,$A5,アタックリスト!$M$2:$M$305,"セミナー参加")+COUNTIFS(アタックリスト!$C$2:$C$305,$A5,アタックリスト!$M$2:$M$305,"検討中")+COUNTIFS(アタックリスト!$C$2:$C$305,$A5,アタックリスト!$M$2:$M$305,"加盟決定") -> 0 | H5: =COUNTIFS(アタックリスト!$C$2:$C$305,$A5,アタックリスト!$M$2:$M$305,"加盟決定") -> 0
A6: 千葉県 | B6: =COUNTIFS(アタックリスト!$C$2:$C$305,$A6,アタックリスト!$B$2:$B$305,"A") -> 2 | C6: =COUNTIFS(アタックリスト!$C$2:$C$305,$A6,アタックリスト!$B$2:$B$305,"B") -> 9 | D6: =COUNTIFS(アタックリスト!$C$2:$C$305,$A6,アタックリスト!$B$2:$B$305,"C") -> 7 | E6: =SUM(B6:D6) -> 18 | F6: =COUNTIFS(アタックリスト!$C$2:$C$305,$A6,アタックリスト!$M$2:$M$305,"<>未着手",アタックリスト!$M$2:$M$305,"<>") -> 0 | G6: =COUNTIFS(アタックリスト!$C$2:$C$305,$A6,アタックリスト!$M$2:$M$305,"商談中")+COUNTIFS(アタックリスト!$C$2:$C$305,$A6,アタックリスト!$M$2:$M$305,"セミナー参加")+COUNTIFS(アタックリスト!$C$2:$C$305,$A6,アタックリスト!$M$2:$M$305,"検討中")+COUNTIFS(アタックリスト!$C$2:$C$305,$A6,アタックリスト!$M$2:$M$305,"加盟決定") -> 0 | H6: =COUNTIFS(アタックリスト!$C$2:$C$305,$A6,アタックリスト!$M$2:$M$305,"加盟決定") -> 0
A7: 静岡県 | B7: =COUNTIFS(アタックリスト!$C$2:$C$305,$A7,アタックリスト!$B$2:$B$305,"A") -> 2 | C7: =COUNTIFS(アタックリスト!$C$2:$C$305,$A7,アタックリスト!$B$2:$B$305,"B") -> 12 | D7: =COUNTIFS(アタックリスト!$C$2:$C$305,$A7,アタックリスト!$B$2:$B$305,"C") -> 5 | E7: =SUM(B7:D7) -> 19 | F7: =COUNTIFS(アタックリスト!$C$2:$C$305,$A7,アタックリスト!$M$2:$M$305,"<>未着手",アタックリスト!$M$2:$M$305,"<>") -> 0 | G7: =COUNTIFS(アタックリスト!$C$2:$C$305,$A7,アタックリスト!$M$2:$M$305,"商談中")+COUNTIFS(アタックリスト!$C$2:$C$305,$A7,アタックリスト!$M$2:$M$305,"セミナー参加")+COUNTIFS(アタックリスト!$C$2:$C$305,$A7,アタックリスト!$M$2:$M$305,"検討中")+COUNTIFS(アタックリスト!$C$2:$C$305,$A7,アタックリスト!$M$2:$M$305,"加盟決定") -> 0 | H7: =COUNTIFS(アタックリスト!$C$2:$C$305,$A7,アタックリスト!$M$2:$M$305,"加盟決定") -> 0
A8: 愛知県 | B8: =COUNTIFS(アタックリスト!$C$2:$C$305,$A8,アタックリスト!$B$2:$B$305,"A") -> 2 | C8: =COUNTIFS(アタックリスト!$C$2:$C$305,$A8,アタックリスト!$B$2:$B$305,"B") -> 6 | D8: =COUNTIFS(アタックリスト!$C$2:$C$305,$A8,アタックリスト!$B$2:$B$305,"C") -> 8 | E8: =SUM(B8:D8) -> 16 | F8: =COUNTIFS(アタックリスト!$C$2:$C$305,$A8,アタックリスト!$M$2:$M$305,"<>未着手",アタックリスト!$M$2:$M$305,"<>") -> 0 | G8: =COUNTIFS(アタックリスト!$C$2:$C$305,$A8,アタックリスト!$M$2:$M$305,"商談中")+COUNTIFS(アタックリスト!$C$2:$C$305,$A8,アタックリスト!$M$2:$M$305,"セミナー参加")+COUNTIFS(アタックリスト!$C$2:$C$305,$A8,アタックリスト!$M$2:$M$305,"検討中")+COUNTIFS(アタックリスト!$C$2:$C$305,$A8,アタックリスト!$M$2:$M$305,"加盟決定") -> 0 | H8: =COUNTIFS(アタックリスト!$C$2:$C$305,$A8,アタックリスト!$M$2:$M$305,"加盟決定") -> 0
A9: 石川県 | B9: =COUNTIFS(アタックリスト!$C$2:$C$305,$A9,アタックリスト!$B$2:$B$305,"A") -> 2 | C9: =COUNTIFS(アタックリスト!$C$2:$C$305,$A9,アタックリスト!$B$2:$B$305,"B") -> 7 | D9: =COUNTIFS(アタックリスト!$C$2:$C$305,$A9,アタックリスト!$B$2:$B$305,"C") -> 7 | E9: =SUM(B9:D9) -> 16 | F9: =COUNTIFS(アタックリスト!$C$2:$C$305,$A9,アタックリスト!$M$2:$M$305,"<>未着手",アタックリスト!$M$2:$M$305,"<>") -> 0 | G9: =COUNTIFS(アタックリスト!$C$2:$C$305,$A9,アタックリスト!$M$2:$M$305,"商談中")+COUNTIFS(アタックリスト!$C$2:$C$305,$A9,アタックリスト!$M$2:$M$305,"セミナー参加")+COUNTIFS(アタックリスト!$C$2:$C$305,$A9,アタックリスト!$M$2:$M$305,"検討中")+COUNTIFS(アタックリスト!$C$2:$C$305,$A9,アタックリスト!$M$2:$M$305,"加盟決定") -> 0 | H9: =COUNTIFS(アタックリスト!$C$2:$C$305,$A9,アタックリスト!$M$2:$M$305,"加盟決定") -> 0
A10: 香川県 | B10: =COUNTIFS(アタックリスト!$C$2:$C$305,$A10,アタックリスト!$B$2:$B$305,"A") -> 3 | C10: =COUNTIFS(アタックリスト!$C$2:$C$305,$A10,アタックリスト!$B$2:$B$305,"B") -> 9 | D10: =COUNTIFS(アタックリスト!$C$2:$C$305,$A10,アタックリスト!$B$2:$B$305,"C") -> 6 | E10: =SUM(B10:D10) -> 18 | F10: =COUNTIFS(アタックリスト!$C$2:$C$305,$A10,アタックリスト!$M$2:$M$305,"<>未着手",アタックリスト!$M$2:$M$305,"<>") -> 0 | G10: =COUNTIFS(アタックリスト!$C$2:$C$305,$A10,アタックリスト!$M$2:$M$305,"商談中")+COUNTIFS(アタックリスト!$C$2:$C$305,$A10,アタックリスト!$M$2:$M$305,"セミナー参加")+COUNTIFS(アタックリスト!$C$2:$C$305,$A10,アタックリスト!$M$2:$M$305,"検討中")+COUNTIFS(アタックリスト!$C$2:$C$305,$A10,アタックリスト!$M$2:$M$305,"加盟決定") -> 0 | H10: =COUNTIFS(アタックリスト!$C$2:$C$305,$A10,アタックリスト!$M$2:$M$305,"加盟決定") -> 0
A11: 合計 | B11: =SUM(B5:B10) -> 14 | C11: =SUM(C5:C10) -> 47 | D11: =SUM(D5:D10) -> 43 | E11: =SUM(E5:E10) -> 104 | F11: =SUM(F5:F10) -> 0 | G11: =SUM(G5:G10) -> 0 | H11: =SUM(H5:H10) -> 0
A13: ステータス別
A14: 未着手 | B14: =COUNTIF(アタックリスト!$M$2:$M$305,A14) -> 104
A15: 資料送付 | B15: =COUNTIF(アタックリスト!$M$2:$M$305,A15) -> 0
A16: アポ獲得 | B16: =COUNTIF(アタックリスト!$M$2:$M$305,A16) -> 0
A17: 商談中 | B17: =COUNTIF(アタックリスト!$M$2:$M$305,A17) -> 0
A18: セミナー参加 | B18: =COUNTIF(アタックリスト!$M$2:$M$305,A18) -> 0
A19: 検討中 | B19: =COUNTIF(アタックリスト!$M$2:$M$305,A19) -> 0
A20: 加盟決定 | B20: =COUNTIF(アタックリスト!$M$2:$M$305,A20) -> 0
A21: 見送り | B21: =COUNTIF(アタックリスト!$M$2:$M$305,A21) -> 0
A22: 対象外 | B22: =COUNTIF(アタックリスト!$M$2:$M$305,A22) -> 0
A24: 2026年12月末 全国50社目標（PR TIMES発表）に対する重点6県からの加盟決定数 | H24: =H11 -> 0

Sheet LIFE X概要・トーク
A1: ■ LIFE X 概要（公開情報ベース）
A2: 運営 | B2: 株式会社Gハウス（大阪）
A3: 開始 | B3: 2026年4月1日。開始2ヶ月で加盟15社突破、施主からの問い合わせ300件以上
A4: 目標 | B4: 2026年12月末までに全国50社
A5: 料金体系 | B5: 棟数に応じたロイヤリティなし。加盟金＋月会費のみ（金額は公開情報では未確認）
A6: 重点募集エリア | B6: 神奈川・千葉・静岡・愛知・石川・香川（いずれも既存加盟店なし）
A7: 価格 | B7: 本体1,890万円〜（税込2,079万円）、坪単価60万円前後
A8: プラン | B8: 平屋・2階建て 70プラン以上（有名建築家プランも予定）
A9: 性能 | B9: 耐震等級3（許容応力度計算）・制振ダンパー／断熱等級6（UA値0.46）／C値0.24／第一種全熱交換換気／太陽光標準（最大11.16kW）／省令準耐火
A10: 設備 | B10: GRAFTEKTキッチン、BOSCH食洗機 など
A11: 集客支援 | B11: GハウスのWeb集客ノウハウを加盟店エリアに展開（Gハウス実績：昨年対比約140%超）
A13: ■ 競合FCの費用水準（比較メディア等の2次情報。商談前に最新情報を確認）
A14: アイフルホーム | B14: 加盟金400万円（税別）／月額固定30万円＋延床1㎡あたり1,700〜2,200円／約380エリア完全テリトリー制
A15: R+house | B15: 加盟金500万円前後／契約1棟ごとにロイヤリティ
A16: ジブンハウス | B16: 費用非公開／store型は1エリア1店舗、instore型は店舗数制限なし
A17: 業界相場 | B17: 加盟金200〜500万円、月額20〜30万円＋棟数課金が一般的
A19: ■ 刺さるトーク（タイプ別）
A20: 注文住宅のみの工務店 | B20: 「高単価の注文住宅は残したまま、2,000万円前後の一次取得層向けの商品を、開発費ゼロで追加できます」
A21: 棟数を伸ばしたいビルダー | B21: 「棟数が増えてもロイヤリティは増えません。売れるほど利益が残る仕組みです」
A22: 他FC加盟済みの工務店 | B22: 「今のFCと併用しやすい月会費制です。棟数課金のFCと比べて、総コストを試算してみませんか」
A23: 集客に悩む工務店 | B23: 「Gハウスで成果が出たWeb集客の型を、エリアにそのまま展開します。開始2ヶ月で問い合わせ300件以上です」
A24: 高性能住宅を作りたい工務店 | B24: 「等級3・断熱等級6・C値0.24・太陽光標準の仕様を、規格化した価格で出せます」
A25: 石川県（能登復興） | B25: 「耐震等級3＋制振の規格住宅なら、再建需要に短い工期・明確な価格で応えられます」
A27: ■ 出典
A28: PR TIMES | B28: https://prtimes.jp/main/html/rd/p/000000060.000159579.html
A29: PR TIMES | B29: https://prtimes.jp/main/html/rd/p/000000053.000159579.html
A30: 公式 | B30: https://lifex-house.jp/

Sheet 除外_既存加盟店
A1: 地域 | B1: 都道府県 | C1: 社名（LIFE X加盟済み）
A2: 東北 | B2: 岩手県 | C2: シリウス
A3: 東北 | B3: 福島県 | C3: スピークス
A4: 関東 | B4: 栃木県 | C4: Life&Design
A5: 関東 | B5: 埼玉県・東京都 | C5: YUNO HOME
A6: 中部 | B6: 新潟県 | C6: ダイケンアーキテクツ／大建建設
A7: 近畿 | B7: 奈良県 | C7: 竹村工務店
A8: 近畿 | B8: 奈良県 | C8: キノシタ
A9: 近畿 | B9: 大阪府 | C9: いえプロ不動産
A10: 中国 | B10: 島根県・鳥取県 | C10: 中央建設
A11: 中国 | B11: 広島県 | C11: 坂本建設工業
A12: 中国 | B12: 広島県 | C12: フラワーホーム／BJC
... A15: 不明 | B15: 未確認 | C15: 建匠
A17: 出典：lifex-house.jp/partner/（検索結果の内容から作成。最新の一覧は公式ページで確認してください）
